AURAI/__init__.py
AURAI/aurai_imputer.py
aurai_imputer-1.1.0.dist-info/LICENSE
aurai_imputer-1.1.0.dist-info/METADATA
aurai_imputer-1.1.0.dist-info/WHEEL
aurai_imputer-1.1.0.dist-info/top_level.txt
aurai_imputer-1.1.0.dist-info/RECORD
