Metadata-Version: 2.1
Name: aurai-imputer
Version: 1.1.0
Summary: AURAI: A uniquely hybrid imputation model that unifies mask-aware variational autoencoding, latent-neighbor correction, and adaptive feature gating to deliver uncertainty-aware reconstruction of missing data.
Home-page: https://github.com/Luckyy0311
Author: Abdul Mofique Siddiqui
Author-email: mofique7860@gmail.com
License: MIT
Classifier: Development Status :: 4 - Beta
Classifier: Intended Audience :: Science/Research
Classifier: License :: OSI Approved :: MIT License
Classifier: Programming Language :: Python :: 3
Classifier: Topic :: Scientific/Engineering :: Artificial Intelligence
Requires-Python: >=3.8
License-File: LICENSE
Requires-Dist: numpy>=1.20
Requires-Dist: pandas>=1.0
Requires-Dist: torch>=1.10
Requires-Dist: scikit-learn>=1.0
